{"id":3558469406,"achievement_count":11,"athlete":{"id":36515485},"athlete_count":1,"average_speed":5.622,"average_watts":233.4,"distance":43506.6,"elapsed_time":7814,"elev_high":642.6,"elev_low":139.6,"end_latlng":[50.53163,14.131046],"external_id":"garmin_push_5034461841","gear_id":"b6986814","kilojoules":1806.4,"kudos_count":7,"map":{"id":"a3558469406","polyline":"gcnsH{jfuAC]?}A@QBSZc@fBmBfDwC~AyAhEyDPEP?~@^VRR?FGTm@T_AZgBr@wFrAkJ|@yFNu@Pm@f@}@x@y@`@UPEH?ZMRYLIRG^C`@Fb@Rt@NHFZb@LHLD\\B\\AFKDO?Q_@qFBQDKJGTBDDRf@f@fAd@|Ah@pCz@nDb@hCFhA@p@GxFMj@IPMJi@^S`@Aj@NfCD|BL|ALnCL^LFLB`@AN@LJFRBTA~FKfIKtEOxDYxDOhAKlFWrE_@pKOtIG`F@p@N|ERzBr@jFLp@X|@h@tCJz@DlAj@pCb@xARb@z@~@Tl@pAbGnAzDr@rCjAtD^z@hDpFjBlDb@l@hCfDrAnBxCpGfArCr@lCbBnJvArKPzA`@`DJl@x@zCd@tBh@fFFpAFvBApAWdFSjB[tB?P@z@Fj@RxA\\rAHl@@VCVGRi@`ACR?j@DTl@|ALj@Fl@FbAEh@KFMBcADwBNYJSV[j@]bAARDh@`@jD?TCPIJKDK@sDAy@Dq@Vm@b@c@f@aAxA{@dA_AzAS`@gE~JgA|BKLIDs@RUTQZ_ArCeArCc@zAc@rAeAdEm@tDe@zBwAtDW^sBjCg@d@aAn@sCbA[LIH]h@]t@gAfBY|@KdAYz@W\\c@b@QLOBQCm@Qi@Gy@F[JeDxCW^_@t@[V]Rs@r@[PuBrB{AhAsBhAwAl@uDbB_DfB}Av@gHbD{@x@cAx@sArAw@fAoBbDO\\Mb@o@vD[xAo@tFWvDUvA[|CMlBEtB?|GCzDMdCGn@_@`COt@i@vDg@zBeAjGs@zDa@pA_AvB_@n@c@r@q@x@gA~@aBdAuAj@cEt@sA~@iAPgEb@iDt@kBbAwItFsAr@kBr@UDg@?iASw@CaD}@cB_@wB_@kFHa@CuDAUEQQa@_AS[eAa@{@c@{D_A_BMyAWuA@MAIKES?UJmANi@JAt@LrBp@bAVVBNE^_@f@w@h@sAj@eBHQ^YVMt@O~B?~AChCWv@MRI\\WbAkAbBwB~BeBb@UfAGXEh@S^Gh@[hAqAPk@N[DQDGd@c@ZO^GHAXLZDXC^FP?FBTC^?|@Lj@AtAVX?\\FPAf@BRNNTn@tAp@n@Tf@t@dA\\p@X`A\\|@TNVFf@HTEXMb@}@x@qA`@y@lAyCFo@H[z@{AjAsCh@iBF]Di@@kBQgDKk@_@cAKa@KQ[}@Yc@k@c@]MM?SNo@p@qAn@M?KEGKCOLi@F_@HcBFc@BqAS_DG}BCe@a@yBGk@Ww@a@s@Qa@{@mCw@}Aa@i@s@o@_B_De@a@q@]UUq@_Au@s@c@c@i@}@a@cAOm@]mCQ{@_@iAIq@M_B?uCGsBBeCGyB?wCHeD?y@Au@EWg@aBa@iBg@_BWoAa@qDKk@Si@Is@[kASeAGm@Cu@MmA]eBEc@IsACuAQaCUsAWiBOc@MWOk@QsBKk@C{@WeBGgAGOKIa@A}@Zq@FeASYAw@IMEMOBk@TgABu@Lw@As@Ba@Ak@J{@Xs@Jg@z@oCNY`@o@f@cBj@u@z@y@?KGg@AmAEWc@U}@}@qAiBs@gAOS[UYIg@Eg@Si@Iw@GqA[aAMKEc@KKIe@IOMQGm@IU?UEQK]c@c@eAQOIESBQHMPk@`AcA`AMDQ@ICaAo@WE{@HSFO@QLg@F[AUBg@Pe@l@OLKBY?qACaAFe@CwBg@SMYe@[cA_@eA_BiDMa@[q@c@gA]m@CK?YBKfAqAPk@@s@KaAAa@Dq@Ji@Pk@R_@|@cAT]d@mAZaADY@a@@sACw@BeA^_EX_BZ{@Rc@`AqAhAqAbAqAt@iAHW@a@g@iCgAuEQa@AOFWPUl@a@LWHk@@w@Cm@QcCGsA@c@TiB`@wNCs@Y_CMiBMqAWkBWoAKs@LKrDcC|AkA`AsABQ?MCIICSDgDrBaA^sE`AcEfAWBc@AmAEa@?gCZq@Fo@BgCQgAJU?aAM[Da@NUAKC[Mk@e@UMYCSIIMI[Eg@DwAC_CCOQg@Ow@Gs@@aACMEBE\\E`AW`CGNIJWJk@H]HWQ[CgCnAeAXgACo@^IBSAWKy@{@WKMAUBKDWT[p@g@j@Ud@YjAc@lAOjBIf@Yr@]f@a@\\e@r@ALDh@Et@Kz@Uz@Ox@s@tAOLWLORIXALB\\AHKLgAT_@BcCKSGaAg@}@_@iAQoAIqDGiANs@?K?MDGLSrAIRc@d@OXD^Rh@Hj@^|DAbAC`AMtAKvCGf@S|@K~@An@BpAEzAGxAO|@QzCKf@UpBKf@Qn@Ef@ERGj@[dAMrAKz@q@lBMPMf@Kv@Qt@w@fC[p@[bASf@eAhBGR_@t@QLWNaAROH[HWBIAKG[CS@QAQD_@DGD_@AIB_@ES?q@MG?u@[I?MIk@s@IQSaACi@Ke@?SIMe@c@OYCMIc@Ci@A{BKs@Qm@Yc@SQqBiAoAeAmAkA{@_AcA}Ai@cAk@oBQaAK{@Uk@WqABUH[D_@Ni@@WH_@BUCGAUHU?UBKFEBEZuA@UBq@CYAi@BUFYCW@WACFUAYBc@?a@Iy@?a@Bk@LmABeA?i@FsAXmCbAsEb@sAd@s@t@o@zAkAPG~A_AREJC\\ArAF`@ERKHIT]La@B]GWQOs@a@_@Y{AuAo@q@y@sBKMy@q@}@k@cAUKAm@Fo@VyBvAe@TSFa@B_@G_@Ig@[_Aw@]Si@Ou@Gg@I}@[eAe@q@G]US[GUIg@q@yAo@_A][s@iAcAuAu@}@e@Wa@Qc@OoA]SQYi@[a@QEm@DQEe@c@UOgA_@w@Qk@C[@w@JMAQMIUAY@Uj@aJHcBP{AF_ARwAl@aCn@gBLWJGt@Y`@qARa@`@mAAKCMmByDSg@Ii@EsEDoBNiAd@sBNiAR_FN_CPgEDe@F}A@eBEyBUyHOkB[cCQSIEM?eALy@LmA?IAKIGOE[@c@Pq@^i@fAy@b@e@HOJc@@SFyABcBNyG@{EAoGDcFA{@Ke@IMKI]Kc@Gc@Ka@Uc@[c@a@s@{@eAyAG_@AmAL{BBMHGHADDJZD`@LXp@b@p@v@Z`@J\\HNLDJ?DMFcAXsAVaALq@J]Xg@h@o@POl@YhAkALChAu@XMVCBCXa@l@uARURIp@KVIJGDITK`@ANB\\ERQz@_Bh@_@h@MpAHPEJ?`@O@EDCL@PF^AJCl@eBLUVUd@}@^[`@O`AQd@DZHb@H^?h@Op@a@HAHKF?DC^GXMR@RDJLNHR@LIB?TFFCFK@FDCZk@VS^Ob@Md@E\\QNWPe@JQHIBIbAwAVc@Ro@@cAFs@Ro@j@iAh@c@PIl@QPAREN?PG^BTCN?\\DlARj@X|@V|@F\\AZMt@e@xA[xCBnAKv@HNAtBu@j@E`A?~Ba@|AO|Ba@rAJbC\\j@?f@MxAs@ROTUZu@Lu@JaABkAX_DTkAp@wBx@mAz@q@NS^_A^kAdAgCLq@R}Bb@mB^oALQh@]Zc@l@i@RM`AO|@[n@I~@SNA`ALnAFNCrA]b@@dALj@?NBd@Nv@Hv@VNCH@LEZAVIH@LFPCF@FDRB^NVPl@RFIJg@Na@LMV_@ZYR[z@wB?GHO`@qACIWY[SIO]a@c@WSWO_@]e@{B_BWUeBmCGU?[Fi@Be@Fi@Jc@BQ@UFSFEF?h@Fx@n@HDP?HCJANBb@XTDNCj@YREVD^Rn@HXHnAL`@?PA\\Kd@Yd@GN@NBNJZZX^T~@LpA?nAOhAOb@[j@Mb@AR@T\\lBDx@GfA?t@Hl@XbAH`A?v@Mx@gBlGq@`F[pA_@|@u@n@mArCqA~A_@\\}@l@MHg@JWJc@^aAPg@Nw@^Q?WIY?KL[x@[ZYJe@BMFQNAVRn@d@lAJPT\\JLf@`@b@Td@\\d@j@NXN`@Tt@R`ANfAFlAAfAMzCItDEZKV]b@_@z@AL?PJt@b@^\\JPJb@`@RVr@rA~@hARl@H~@DTTf@rBpBxAxBPNRJ|@PhBp@tAN^ADFBV?NItBKn@y@xBAPDPd@x@b@`@RFfA?f@Ft@Tf@Tb@h@jB~CDT^tDL|@ALEHKDWIg@GU@KFEROfBCr@BXA^NZHd@dArDlAlBf@d@X\\t@|AV\\XNJ@LCLELKV[PMF@DDNd@HHXJPAbAQPAb@JzALNDRNH?PEv@E\\EN?^DJFT\\RPVNz@X\\V|@rAn@fApAfBbAdAj@^r@v@h@r@ZVTz@HPHJl@Zn@Nf@FLFp@f@`@b@Hb@LVJFXBj@Jf@CHEHc@d@{@HILGTCb@Mb@GF@bAXh@HZA|@Dj@Op@]|@o@b@Wd@MfCc@hCg@nCs@tAUNAb@FfC`Ah@^`@h@Xj@Nj@?b@KZ?T~@hD\\z@Xd@rAzAd@Tf@Nb@Pl@^TRHEJQRm@JKHCH?f@N|Az@~AzAbAlALHx@`@`@Fv@@fC_@d@Ab@@b@HbD~@ZTPD\\E`A[fCgAdDoAn@[jDsCfEeDz@w@RKHALHNRBN@v@C|A?`BDh@DLHDXELKZU~@cATSzAw@NEp@@RCTEh@[hA_APKPE`@CN@XL^sAtDqFZYxAaCb@m@d@g@ZWNKx@WHK?B?K","summary_polyline":"gcnsH{jfuA@aDbCqCpMkLvCd@jAkFpE}ZbByC~DeBxFhBQ_Hj@a@fBrEdCrLDlKcBjCAj@p@rNpBjABnEYbReCzl@OlKd@jKbElWhCjF`HhWtHzM`GdItGrPnF`_@tCfPLzGgAxMfAzIy@lD`A~CHzCcGdAy@nBd@hFMr@wHb@oEjFcJzRqBxAmEvMyCvNwAtDsDpE{FjCcCfEwA|EeAt@_EIyP~Og\\~OsEfEgDjFiBrIyBbTm@rZ{Fr\\aBhEuB|CiDdCmJ`D{LjBcS`L}PoCcMB}AsBaCeAyMeBIeB`@iAtGtArEeIvNiAdIaIxF{AvBsD`B{@zNbApExGtApDpBXrCuEfFuMp@gCFuC]sEmByEwAq@uCpBa@Qf@sHiAiN_EyJuDyFyFmF{AoDgBeLCw\\oCsK{BmM}AgR{AeHaAiKyIm@v@_LzDyKfBoBOyCsGoH}PkDoBkCqDhDuBw@kEj@iBpAkIg@yH}P|AcDDsFzD}HHmGx@_H~HwLaCsL~AsC[}Hx@eSuB_R~G{EdAsBkGjCwKhCqWb@kD}BC_Go@sFi@dFi@f@}BAoIhC}BuAgA\\yAbCqB`JeBxBAlBq@pDkBdCU|AkFLmHkBiIL[`B}@rA`AvJsBf^iCnPkBtGcCdH_C`EyI`A{Dy@u@eAc@eDcAyAm@kHoFeEmEiFaDoLdBwKb@iV|AaJhAgCpC{BdCmArDOl@iACu@aEaDuBsDwB}A}BOeGpCeEyB}HkBuBiE{FyH{DwAiA}AmGkBiD[bBiV|AiFnAy@vAaEgC{FO}FjAwJdAqW[sLk@oFwF@c@w@RuAjCiCVgA^cf@a@}@gCu@{ByBeAyAImBL{B\\Q^vAnDpDrB_JrDeDlCoAzAmCtEaAxBqCnG_@xBoE`Ak@fEFvDyA~B^jAkA~Bo@~CeFp@wEfBwBzDa@pHpAjDoApH?~PoCbGh@`CaAdA{Av@cJfAcEdCsCdCsGdBmJ`C}BbGwAdGMhMx@`C~@xBwDfBaFyIuIeBmCd@kGnFtAnAc@rFz@jCm@tAjAb@pCOxC{@fC\\zHl@jFcEzRuG~JoDnBeFv@cAbBaB~@zAlDrDhDhA`FQfNoArCHtAjCpBrB|Cx@jD~EzFvHdBE|CaAlEhAzA`Fz@nChEp@vGsBFWhF~AtF|ElHr@LdA{@`AbAlLLfDxB~DbGhFhFh@xArCz@jBfCpAVp@Ix@iBfAYrF`@dFcCjPoCrEjCh@vAKtA~@hDjC|DtDjBt@qAz@JhIpGjHUtFdB|LuEbM}Jj@j@AvFT|@tFwDjBMvCmBjAJ^sAnI{LtCwB"},"max_speed":14.8,"moving_time":7738,"name":"Po úspěšne failnuté zkoušce z Kombinatorické Optimalizace","start_date":"2020-06-03T13:51:07.000Z","start_date_local":"2020-06-03T15:51:07.000Z","start_latlng":[50.54021,14.127986],"timezone":"(GMT+01:00) Europe/Prague","total_elevation_gain":977,"type":"Ride","upload_id":3799476352,"upload_id_str":"3799476352","workout_type":10,"best_efforts":null,"calories":1467,"device_name":"Garmin fēnix 6 Pro","embed_token":"9b5d002abeeaed179a906859d5b6b7b133feab4c","gear":{"distance":3336187,"id":"b6986814","name":"Trek - Superfly 5","resource_state":2},"laps":[{"activity":{"id":3558469406},"athlete":{"id":36515485},"average_speed":8.39,"distance":5000,"elapsed_time":605,"end_index":321,"id":11774303716,"lap_index":1,"max_speed":11.9,"moving_time":596,"name":"Lap 1","split":1,"start_date":"2020-06-03T13:51:07.000Z","start_date_local":"2020-06-03T15:51:07.000Z","total_elevation_gain":14},{"activity":{"id":3558469406},"athlete":{"id":36515485},"average_speed":7.94,"distance":5000,"elapsed_time":630,"end_index":691,"id":11774303718,"lap_index":2,"max_speed":9.6,"moving_time":630,"name":"Lap 2","split":2,"start_date":"2020-06-03T14:01:14.000Z","start_date_local":"2020-06-03T16:01:14.000Z","start_index":322,"total_elevation_gain":37},{"activity":{"id":3558469406},"athlete":{"id":36515485},"average_speed":5.37,"distance":5000,"elapsed_time":931,"end_index":1409,"id":11774303719,"lap_index":3,"max_speed":9.4,"moving_time":931,"name":"Lap 3","split":3,"start_date":"2020-06-03T14:11:45.000Z","start_date_local":"2020-06-03T16:11:45.000Z","start_index":692,"total_elevation_gain":128},{"activity":{"id":3558469406},"athlete":{"id":36515485},"average_speed":4.06,"distance":5000,"elapsed_time":1233,"end_index":2560,"id":11774303720,"lap_index":4,"max_speed":11.2,"moving_time":1233,"name":"Lap 4","split":4,"start_date":"2020-06-03T14:27:16.000Z","start_date_local":"2020-06-03T16:27:16.000Z","start_index":1410,"total_elevation_gain":236},{"activity":{"id":3558469406},"athlete":{"id":36515485},"average_speed":4.55,"distance":5000,"elapsed_time":1099,"end_index":3538,"id":11774303723,"lap_index":5,"max_speed":14.4,"moving_time":1099,"name":"Lap 5","split":5,"start_date":"2020-06-03T14:47:50.000Z","start_date_local":"2020-06-03T16:47:50.000Z","start_index":2561,"total_elevation_gain":180},{"activity":{"id":3558469406},"athlete":{"id":36515485},"average_speed":4.88,"distance":5000,"elapsed_time":1025,"end_index":4479,"id":11774303726,"lap_index":6,"max_speed":14.8,"moving_time":1025,"name":"Lap 6","split":6,"start_date":"2020-06-03T15:06:09.000Z","start_date_local":"2020-06-03T17:06:09.000Z","start_index":3539,"total_elevation_gain":185},{"activity":{"id":3558469406},"athlete":{"id":36515485},"average_speed":4.88,"distance":5000,"elapsed_time":1036,"end_index":5372,"id":11774303729,"lap_index":7,"max_speed":13.4,"moving_time":1024,"name":"Lap 7","split":7,"start_date":"2020-06-03T15:23:15.000Z","start_date_local":"2020-06-03T17:23:15.000Z","start_index":4480,"total_elevation_gain":158},{"activity":{"id":3558469406},"athlete":{"id":36515485},"average_speed":6.68,"distance":5000,"elapsed_time":829,"end_index":5994,"id":11774303731,"lap_index":8,"max_speed":13.8,"moving_time":748,"name":"Lap 8","split":8,"start_date":"2020-06-03T15:40:32.000Z","start_date_local":"2020-06-03T17:40:32.000Z","start_index":5373,"total_elevation_gain":27},{"activity":{"id":3558469406},"athlete":{"id":36515485},"average_speed":8.33,"distance":3506.62,"elapsed_time":421,"end_index":6294,"id":11774303735,"lap_index":9,"max_speed":12.8,"moving_time":421,"name":"Lap 9","split":9,"start_date":"2020-06-03T15:54:22.000Z","start_date_local":"2020-06-03T17:54:22.000Z","start_index":5995,"total_elevation_gain":13}],"photos":{},"segment_efforts":[{"distance":3469.5,"elapsed_time":448,"id":2703294315072467755,"start_date":"2020-06-03T14:08:47.000Z","start_date_local":"2020-06-03T16:08:47.000Z","activity":{"id":3558469406},"athlete":{"id":36515485},"average_heartrate":146.8,"average_watts":286.4,"end_index":852,"max_heartrate":158,"moving_time":448,"name":"Labska cyklostezka - Velke Zernoseky - Libochovany","pr_rank":3,"segment":{"activity_type":"Ride","average_grade":0.1,"city":"Velké Žernoseky","country":"Czech Republic","distance":3469.5,"elevation_high":148.8,"elevation_low":139.4,"end_latlng":[50.56209,14.039784],"id":6463307,"maximum_grade":4.7,"name":"Labska cyklostezka - Velke Zernoseky - Libochovany","start_latlng":[50.539623,14.062535],"state":"Ústí nad Labem Region"},"start_index":614},{"distance":3235.6,"elapsed_time":791,"id":2703294315072467807,"start_date":"2020-06-03T14:17:56.000Z","start_date_local":"2020-06-03T16:17:56.000Z","activity":{"id":3558469406},"athlete":{"id":36515485},"average_heartrate":162.1,"average_watts":254.8,"end_index":1619,"max_heartrate":178,"moving_time":791,"name":"Libochovany-Kalvárie-mravenci","pr_rank":2,"segment":{"activity_type":"Ride","average_grade":4.9,"city":"Libochovany","climb_category":1,"country":"Czech Republic","distance":3235.6,"elevation_high":305.6,"elevation_low":147.4,"end_latlng":[50.555233,14.063049],"id":11769087,"maximum_grade":29.5,"name":"Libochovany-Kalvárie-mravenci","start_latlng":[50.56246,14.04269],"state":"Ústí nad Labem Region"},"start_index":901},{"distance":341.2,"elapsed_time":168,"id":2703294315072467765,"start_date":"2020-06-03T14:20:35.000Z","start_date_local":"2020-06-03T16:20:35.000Z","activity":{"id":3558469406},"athlete":{"id":36515485},"average_heartrate":169.3,"average_watts":283.1,"end_index":1211,"max_heartrate":178,"moving_time":168,"name":"Výjezd od Libochovan","pr_rank":2,"segment":{"activity_type":"Ride","average_grade":10.8,"city":"Velké Žernoseky","country":"Czech Republic","distance":341.2,"elevation_high":242.5,"elevation_low":205.8,"end_latlng":[50.553856,14.04602],"id":13550893,"maximum_grade":23.8,"name":"Výjezd od Libochovan","start_latlng":[50.55667,14.045446]},"start_index":1043},{"distance":623.5,"elapsed_time":66,"id":2703294315072467815,"start_date":"2020-06-03T14:30:47.000Z","start_date_local":"2020-06-03T16:30:47.000Z","activity":{"id":3558469406},"athlete":{"id":36515485},"average_heartrate":154.8,"average_watts":86.3,"end_index":1650,"max_heartrate":159,"moving_time":66,"name":"Sjezd od Strážiště do sedla ","pr_rank":3,"segment":{"activity_type":"Ride","average_grade":-6.4,"city":"Velké Žernoseky","country":"Czechia","distance":623.5,"elevation_high":296.2,"elevation_low":256,"end_latlng":[50.556408,14.069362],"id":23603657,"maximum_grade":-1.6,"name":"Sjezd od Strážiště do sedla ","start_latlng":[50.555344,14.060939],"state":"Ústecký kraj"},"start_index":1608},{"distance":623,"elapsed_time":211,"id":2703294315072467823,"start_date":"2020-06-03T14:34:49.000Z","start_date_local":"2020-06-03T16:34:49.000Z","activity":{"id":3558469406},"athlete":{"id":36515485},"average_heartrate":159.2,"average_watts":254.3,"end_index":2026,"max_heartrate":163,"moving_time":211,"name":"Kamýk Hrad","segment":{"activity_type":"Ride","average_grade":7.3,"city":"Kamýk","country":"Czech Republic","distance":623,"elevation_high":341,"elevation_low":293.8,"end_latlng":[50.558155,14.082219],"id":8421610,"maximum_grade":15.3,"name":"Kamýk Hrad","start_latlng":[50.558186,14.077849],"state":"Ústí nad Labem Region"},"start_index":1815},{"distance":1515.9,"elapsed_time":449,"id":2703294315072467861,"start_date":"2020-06-03T14:38:32.000Z","start_date_local":"2020-06-03T16:38:32.000Z","activity":{"id":3558469406},"athlete":{"id":36515485},"average_heartrate":162.1,"average_watts":247.3,"end_index":2472,"max_heartrate":175,"moving_time":449,"name":"Kamýk-Plešivec","pr_rank":3,"segment":{"activity_type":"Ride","average_grade":7.1,"city":"Kamýk","climb_category":1,"country":"Czech Republic","distance":1515.9,"elevation_high":450.9,"elevation_low":340.3,"end_latlng":[50.569164,14.087971],"id":8421619,"maximum_grade":19.9,"name":"Kamýk-Plešivec","start_latlng":[50.558147,14.082776],"state":"Ústí nad Labem Region"},"start_index":2038},{"distance":1099.6,"elapsed_time":379,"id":2703294315072467853,"start_date":"2020-06-03T14:39:19.000Z","start_date_local":"2020-06-03T16:39:19.000Z","activity":{"id":3558469406},"athlete":{"id":36515485},"average_heartrate":162.6,"average_watts":258.8,"end_index":2454,"max_heartrate":175,"moving_time":379,"name":"celý kopec kolem kapličky","segment":{"activity_type":"Ride","average_grade":7.8,"city":"Kamýk","climb_category":1,"country":"Czechia","distance":1099.6,"elevation_high":450.6,"elevation_low":364.3,"end_latlng":[50.568474,14.086564],"id":19738560,"maximum_grade":20.7,"name":"celý kopec kolem kapličky","start_latlng":[50.559658,14.084369],"state":"Ústecký kraj"},"start_index":2085},{"distance":341,"elapsed_time":137,"id":2703294315072467831,"start_date":"2020-06-03T14:39:27.000Z","start_date_local":"2020-06-03T16:39:27.000Z","activity":{"id":3558469406},"athlete":{"id":36515485},"average_heartrate":167.1,"average_watts":285.9,"end_index":2229,"max_heartrate":175,"moving_time":137,"name":"Výjezd od Kamýku","segment":{"activity_type":"Ride","average_grade":10.6,"city":"Hlinná","country":"Czech Republic","distance":341,"elevation_high":396.3,"elevation_low":360,"end_latlng":[50.562805,14.085789],"id":13347368,"maximum_grade":20.9,"name":"Výjezd od Kamýku","start_latlng":[50.55997,14.084389]},"start_index":2092},{"distance":563.9,"elapsed_time":185,"id":2703294315072467839,"start_date":"2020-06-03T14:42:09.000Z","start_date_local":"2020-06-03T16:42:09.000Z","activity":{"id":3558469406},"athlete":{"id":36515485},"average_heartrate":160.4,"average_watts":253.8,"end_index":2430,"max_heartrate":172,"moving_time":185,"name":"Výjezd kolem Plešivce","segment":{"activity_type":"Ride","average_grade":8.4,"city":"Hlinná","country":"Czech Republic","distance":563.9,"elevation_high":443.7,"elevation_low":396.4,"end_latlng":[50.56804,14.085608],"id":13347390,"maximum_grade":20,"name":"Výjezd kolem Plešivce","start_latlng":[50.563374,14.085442]},"start_index":2254},{"distance":1172.6,"elapsed_time":443,"id":2703294315072467873,"start_date":"2020-06-03T15:00:07.000Z","start_date_local":"2020-06-03T17:00:07.000Z","activity":{"id":3558469406},"athlete":{"id":36515485},"average_heartrate":153.6,"average_watts":253.6,"end_index":3620,"max_heartrate":169,"moving_time":443,"name":"za Varhoštěm - 1. část","pr_rank":1,"segment":{"activity_type":"Ride","average_grade":7.8,"city":"Hlinná","climb_category":1,"country":"Czechia","distance":1172.6,"elevation_high":527.6,"elevation_low":432.4,"end_latlng":[50.58986,14.090228],"id":23730349,"maximum_grade":19,"name":"za Varhoštěm - 1. část","start_latlng":[50.5839,14.098903],"state":"Ústecký kraj"},"start_index":3178},{"distance":475.9,"elapsed_time":182,"id":2703294315072467877,"start_date":"2020-06-03T15:08:47.000Z","start_date_local":"2020-06-03T17:08:47.000Z","activity":{"id":3558469406},"athlete":{"id":36515485},"average_heartrate":154.1,"average_watts":268.7,"end_index":3866,"max_heartrate":164,"moving_time":182,"name":"za Varhoštěm - 2. část","pr_rank":1,"segment":{"activity_type":"Ride","average_grade":8.8,"city":"Ústí nad Labem-Střekov","country":"Czechia","distance":475.9,"elevation_high":562.8,"elevation_low":521,"end_latlng":[50.592873,14.102041],"id":23730384,"maximum_grade":17.3,"name":"za Varhoštěm - 2. část","start_latlng":[50.5932,14.095547],"state":"Ústecký kraj"},"start_index":3685},{"distance":4049.9,"elapsed_time":869,"id":2703294315072467891,"start_date":"2020-06-03T15:25:56.000Z","start_date_local":"2020-06-03T17:25:56.000Z","activity":{"id":3558469406},"athlete":{"id":36515485},"average_heartrate":150.9,"average_watts":227.5,"end_index":5366,"kom_rank":2,"max_heartrate":174,"moving_time":869,"name":"Celý dlouhý vrch","segment":{"activity_type":"Ride","average_grade":0.9,"city":"Malečov","country":"Czechia","distance":4049.9,"elevation_high":653.6,"elevation_low":560.4,"end_latlng":[50.570595,14.159328],"id":24004736,"maximum_grade":25.8,"name":"Celý dlouhý vrch","start_latlng":[50.601227,14.140774],"state":"Ústecký kraj"},"start_index":4610},{"distance":5371.2,"elapsed_time":878,"id":2703294315072467909,"start_date":"2020-06-03T15:40:25.000Z","start_date_local":"2020-06-03T17:40:25.000Z","activity":{"id":3558469406},"athlete":{"id":36515485},"average_heartrate":119.6,"average_watts":124.5,"end_index":6031,"kom_rank":1,"max_heartrate":135,"moving_time":802,"name":"Křížových vrch do Ltm podél Pokratického potoka","segment":{"activity_type":"Ride","average_grade":-6.1,"city":"Žitenice","country":"Czechia","distance":5371.2,"elevation_high":596.4,"elevation_low":266.2,"end_latlng":[50.555737,14.128789],"id":24004757,"maximum_grade":18.2,"name":"Křížových vrch do Ltm podél Pokratického potoka","start_latlng":[50.570595,14.159328],"state":"Ústecký kraj"},"start_index":5366},{"distance":317.1,"elapsed_time":61,"id":2703294315072467903,"start_date":"2020-06-03T15:43:02.000Z","start_date_local":"2020-06-03T17:43:02.000Z","activity":{"id":3558469406},"athlete":{"id":36515485},"average_heartrate":121.5,"end_index":5503,"max_heartrate":131,"moving_time":61,"name":"Sjezd z Křížové hory","pr_rank":1,"segment":{"activity_type":"Ride","average_grade":-15.8,"city":"Žitenice","country":"Czech Republic","distance":317.1,"elevation_high":529.4,"elevation_low":479.3,"end_latlng":[50.571453,14.165084],"id":13607896,"maximum_grade":8.5,"name":"Sjezd z Křížové hory","start_latlng":[50.570118,14.162125]},"start_index":5446},{"distance":1165.3,"elapsed_time":115,"id":2864588886114868472,"start_date":"2020-06-03T15:48:05.000Z","start_date_local":"2020-06-03T17:48:05.000Z","activity":{"id":3558469406},"athlete":{"id":36515485},"average_heartrate":121.9,"average_watts":196.5,"end_index":5800,"max_heartrate":133,"moving_time":115,"name":"Sešup okolo střelnice do Skalice","pr_rank":1,"segment":{"activity_type":"Ride","average_grade":-6.4,"city":"Žitenice","country":"Czechia","distance":1165.3,"elevation_high":426.8,"elevation_low":352.8,"end_latlng":[50.56734,14.142083],"id":29594058,"maximum_grade":2.8,"name":"Sešup okolo střelnice do Skalice","start_latlng":[50.572445,14.152843],"state":"Ústecký kraj"},"start_index":5696},{"distance":1344.6,"elapsed_time":200,"id":2703294315072467921,"start_date":"2020-06-03T15:51:40.000Z","start_date_local":"2020-06-03T17:51:40.000Z","activity":{"id":3558469406},"athlete":{"id":36515485},"average_heartrate":110.9,"average_watts":68.4,"end_index":6028,"max_heartrate":118,"moving_time":182,"name":"Pokratický potok - Skalice rybník","segment":{"activity_type":"Ride","average_grade":-5,"distance":1344.6,"elevation_high":330.1,"elevation_low":263.3,"end_latlng":[50.5557,14.128531],"id":12031819,"maximum_grade":1,"name":"Pokratický potok - Skalice rybník","start_latlng":[50.56565,14.136471]},"start_index":5883}],"splits_metric":[{"average_speed":8.72,"distance":1002.9,"elapsed_time":115,"elevation_difference":-22.2,"moving_time":115,"split":1},{"average_speed":7.26,"distance":1001.7,"elapsed_time":147,"elevation_difference":-7.8,"moving_time":138,"split":2},{"average_speed":8.32,"distance":998.7,"elapsed_time":120,"elevation_difference":1,"moving_time":120,"split":3},{"average_speed":9.42,"distance":998.2,"elapsed_time":106,"elevation_difference":-5.2,"moving_time":106,"split":4},{"average_speed":8.49,"distance":1001.5,"elapsed_time":118,"elevation_difference":3.6,"moving_time":118,"split":5},{"average_speed":7.95,"distance":1002.2,"elapsed_time":126,"elevation_difference":-1.2,"moving_time":126,"split":6},{"average_speed":7.49,"distance":995.7,"elapsed_time":133,"elevation_difference":6.4,"moving_time":133,"split":7},{"average_speed":8.08,"distance":1001.8,"elapsed_time":124,"elevation_difference":-9.4,"moving_time":124,"split":8},{"average_speed":8.02,"distance":1026.6,"elapsed_time":128,"elevation_difference":-2.4,"moving_time":128,"split":9},{"average_speed":8.13,"distance":975.5,"elapsed_time":120,"elevation_difference":4.6,"moving_time":120,"split":10},{"average_speed":8.39,"distance":1014.6,"elapsed_time":121,"elevation_difference":-2.4,"moving_time":121,"split":11},{"average_speed":7.12,"distance":983.2,"elapsed_time":138,"elevation_difference":6.4,"moving_time":138,"split":12},{"average_speed":6.97,"distance":1003,"elapsed_time":144,"elevation_difference":1.6,"moving_time":144,"split":13},{"average_speed":2.99,"distance":996.5,"elapsed_time":333,"elevation_difference":83.2,"moving_time":333,"split":14},{"average_speed":5.12,"distance":998.3,"elapsed_time":195,"elevation_difference":8.8,"moving_time":195,"split":15},{"average_speed":4.48,"distance":1011.9,"elapsed_time":226,"elevation_difference":37.4,"moving_time":226,"split":16},{"average_speed":5.59,"distance":989.6,"elapsed_time":177,"elevation_difference":-3.2,"moving_time":177,"split":17},{"average_speed":3.09,"distance":1001.2,"elapsed_time":324,"elevation_difference":72.2,"moving_time":324,"split":18},{"average_speed":2.84,"distance":997.3,"elapsed_time":351,"elevation_difference":79.6,"moving_time":351,"split":19},{"average_speed":6.45,"distance":1006.9,"elapsed_time":156,"elevation_difference":-7.4,"moving_time":156,"split":20},{"average_speed":7.86,"distance":998.8,"elapsed_time":127,"elevation_difference":-34.8,"moving_time":127,"split":21},{"average_speed":4.95,"distance":994.3,"elapsed_time":201,"elevation_difference":30.6,"moving_time":201,"split":22},{"average_speed":3.65,"distance":1002.4,"elapsed_time":275,"elevation_difference":39,"moving_time":275,"split":23},{"average_speed":7.52,"distance":1000.2,"elapsed_time":133,"elevation_difference":-60.8,"moving_time":133,"split":24},{"average_speed":2.75,"distance":997.3,"elapsed_time":363,"elevation_difference":86.6,"moving_time":363,"split":25},{"average_speed":3.99,"distance":1000.7,"elapsed_time":251,"elevation_difference":31.6,"moving_time":251,"split":26},{"average_speed":4.58,"distance":999.2,"elapsed_time":218,"elevation_difference":17,"moving_time":218,"split":27},{"average_speed":7.22,"distance":1011,"elapsed_time":140,"elevation_difference":-8.6,"moving_time":140,"split":28},{"average_speed":5.98,"distance":992,"elapsed_time":166,"elevation_difference":-22,"moving_time":166,"split":29},{"average_speed":3.99,"distance":1001.7,"elapsed_time":251,"elevation_difference":54.2,"moving_time":251,"split":30},{"average_speed":5.36,"distance":997.5,"elapsed_time":186,"elevation_difference":-3.4,"moving_time":186,"split":31},{"average_speed":3.55,"distance":998.4,"elapsed_time":281,"elevation_difference":16.6,"moving_time":281,"split":32},{"average_speed":3.55,"distance":1004,"elapsed_time":283,"elevation_difference":64.8,"moving_time":283,"split":33},{"average_speed":8.97,"distance":1004.3,"elapsed_time":112,"elevation_difference":-29.2,"moving_time":112,"split":34},{"average_speed":6.09,"distance":992,"elapsed_time":175,"elevation_difference":-16.8,"moving_time":163,"split":35},{"average_speed":4.7,"distance":1006.5,"elapsed_time":279,"elevation_difference":-134.6,"moving_time":214,"split":36},{"average_speed":6.96,"distance":994.8,"elapsed_time":143,"elevation_difference":-13.6,"moving_time":143,"split":37},{"average_speed":8.22,"distance":1002.7,"elapsed_time":122,"elevation_difference":-58,"moving_time":122,"split":38},{"average_speed":7.85,"distance":997.5,"elapsed_time":127,"elevation_difference":-44.8,"moving_time":127,"split":39},{"average_speed":7.03,"distance":998.7,"elapsed_time":158,"elevation_difference":-57.8,"moving_time":142,"split":40},{"average_speed":8.6,"distance":1006.3,"elapsed_time":117,"elevation_difference":-39.2,"moving_time":117,"split":41},{"average_speed":9.2,"distance":1021.4,"elapsed_time":111,"elevation_difference":-50.6,"moving_time":111,"split":42},{"average_speed":8.86,"distance":974.2,"elapsed_time":110,"elevation_difference":-20.4,"moving_time":110,"split":43},{"average_speed":6.07,"distance":503.4,"elapsed_time":83,"elevation_difference":-5.8,"moving_time":83,"split":44}],"splits_standard":[{"average_speed":7.78,"distance":1625.4,"elapsed_time":218,"elevation_difference":-30.4,"moving_time":209,"split":1},{"average_speed":8.46,"distance":1607,"elapsed_time":190,"elevation_difference":1,"moving_time":190,"split":2},{"average_speed":8.99,"distance":1608.8,"elapsed_time":179,"elevation_difference":-1.2,"moving_time":179,"split":3},{"average_speed":7.89,"distance":1608.8,"elapsed_time":204,"elevation_difference":0.8,"moving_time":204,"split":4},{"average_speed":7.87,"distance":1604.9,"elapsed_time":204,"elevation_difference":-4.4,"moving_time":204,"split":5},{"average_speed":8.02,"distance":1604.4,"elapsed_time":200,"elevation_difference":-2.4,"moving_time":200,"split":6},{"average_speed":8.26,"distance":1635.8,"elapsed_time":198,"elevation_difference":2.6,"moving_time":198,"split":7},{"average_speed":6.95,"distance":1584.4,"elapsed_time":228,"elevation_difference":4.6,"moving_time":228,"split":8},{"average_speed":3.48,"distance":1609.7,"elapsed_time":463,"elevation_difference":99.2,"moving_time":463,"split":9},{"average_speed":5.04,"distance":1611.8,"elapsed_time":320,"elevation_difference":28.2,"moving_time":320,"split":10},{"average_speed":3.94,"distance":1602.2,"elapsed_time":407,"elevation_difference":58.4,"moving_time":407,"split":11},{"average_speed":3.23,"distance":1609,"elapsed_time":498,"elevation_difference":88,"moving_time":498,"split":12},{"average_speed":7.63,"distance":1624.9,"elapsed_time":213,"elevation_difference":-28.8,"moving_time":213,"split":13},{"average_speed":4.37,"distance":1601.2,"elapsed_time":366,"elevation_difference":39.8,"moving_time":366,"split":14},{"average_speed":5.83,"distance":1602.1,"elapsed_time":275,"elevation_difference":-31.8,"moving_time":275,"split":15},{"average_speed":3.26,"distance":1614.6,"elapsed_time":495,"elevation_difference":84.6,"moving_time":495,"split":16},{"average_speed":4.55,"distance":1607.3,"elapsed_time":353,"elevation_difference":32.8,"moving_time":353,"split":17},{"average_speed":6.21,"distance":1608.4,"elapsed_time":259,"elevation_difference":-20.4,"moving_time":259,"split":18},{"average_speed":4.71,"distance":1615.9,"elapsed_time":343,"elevation_difference":47,"moving_time":343,"split":19},{"average_speed":3.53,"distance":1601.5,"elapsed_time":454,"elevation_difference":47,"moving_time":454,"split":20},{"average_speed":5.36,"distance":1612.8,"elapsed_time":301,"elevation_difference":15,"moving_time":301,"split":21},{"average_speed":5.48,"distance":1607,"elapsed_time":370,"elevation_difference":-113.4,"moving_time":293,"split":22},{"average_speed":6.44,"distance":1609.8,"elapsed_time":250,"elevation_difference":-59.2,"moving_time":250,"split":23},{"average_speed":8.74,"distance":1608.8,"elapsed_time":184,"elevation_difference":-91.2,"moving_time":184,"split":24},{"average_speed":6.97,"distance":1609.3,"elapsed_time":247,"elevation_difference":-74,"moving_time":231,"split":25},{"average_speed":8.73,"distance":1624.5,"elapsed_time":186,"elevation_difference":-75.6,"moving_time":186,"split":26},{"average_speed":8.89,"distance":1599.3,"elapsed_time":180,"elevation_difference":-28.8,"moving_time":180,"split":27},{"average_speed":1.62,"distance":47,"elapsed_time":29,"elevation_difference":-3.8,"moving_time":29,"split":28}]}