{"id":5235732227,"athlete":{"id":36515485},"athlete_count":1,"average_speed":0.633,"distance":401.6,"elapsed_time":1232,"elev_high":140.5,"elev_low":140.3,"end_latlng":[50.521473,14.06774],"external_id":"garmin_push_6716149490","kudos_count":12,"map":{"id":"a5235732227","polyline":"aojsHcrztA]@I@c@^MT~@u@JCLDg@BUHY\\IXj@s@JG`@Kc@HYLSVAPRUP[JKVIN@k@FWJf@_@HCN?AI@HF?JFJ?","summary_polyline":"aojsHcrztA]@I@c@^MT~@u@JCLDg@BUHY\\IXj@s@JG`@Kc@HYLSVAPRUP[JKVIN@k@FWJf@_@HCN?AI@HF?JFJ?"},"max_speed":1.1,"moving_time":634,"name":"Aklimatizace a tak","start_date":"2021-05-03T14:03:03.000Z","start_date_local":"2021-05-03T16:03:03.000Z","start_latlng":[50.52161,14.067706],"timezone":"(GMT+01:00) Europe/Prague","type":"Swim","upload_id":5578766587,"upload_id_str":"5578766587","best_efforts":null,"calories":88,"description":"Stále to studí, stále mi to nejde, stále zavřené bazény, jen motivace je trochu víc","device_name":"Garmin fēnix 6 Pro","embed_token":"58be4fe6f00463ce52aaa6a40b725403fedfa1be","laps":[{"activity":{"id":5235732227},"athlete":{"id":36515485},"average_cadence":33,"average_speed":0.63,"distance":401.59,"elapsed_time":1232,"end_index":643,"id":17062825915,"lap_index":1,"max_speed":1.1,"moving_time":634,"name":"Lap 1","split":1,"start_date":"2021-05-03T14:03:03.000Z","start_date_local":"2021-05-03T16:03:03.000Z"}],"photos":{},"segment_efforts":[],"splits_metric":[{"average_speed":0.63,"distance":401.6,"elapsed_time":1233,"elevation_difference":-0.2,"moving_time":636,"split":1}],"splits_standard":[{"average_speed":0.63,"distance":401.6,"elapsed_time":1233,"elevation_difference":-0.2,"moving_time":636,"split":1}]}